groqa/__init__.py
groqa/groqa.py
groqa-0.0.5.dist-info/METADATA
groqa-0.0.5.dist-info/WHEEL
groqa-0.0.5.dist-info/top_level.txt
groqa-0.0.5.dist-info/RECORD
