Metadata-Version: 2.1
Name: groqa
Version: 0.0.5
Summary: A Python client for the GROQA API
Home-page: https://github.com/YassKhazzan/groqa_python_library
Author: groqa.com
Author-email: "groqa.com" <support@groqa.com>
Project-URL: Homepage, https://github.com/YassKhazzan/groqa_python_library
Classifier: Intended Audience :: Developers
Classifier: License :: OSI Approved :: MIT License
Classifier: Operating System :: OS Independent
Classifier: Programming Language :: Python :: 3.8
Classifier: Programming Language :: Python :: 3.9
Classifier: Programming Language :: Python :: 3.10
Classifier: Programming Language :: Python :: 3.11
Classifier: Programming Language :: Python :: 3.12
Requires-Python: >=3.8
Requires-Dist: httpx<1.0,>=0.26.0
